setup.py
h5wqueue/__init__.py
h5wqueue/writers.py
h5wqueue.egg-info/PKG-INFO
h5wqueue.egg-info/SOURCES.txt
h5wqueue.egg-info/dependency_links.txt
h5wqueue.egg-info/requires.txt
h5wqueue.egg-info/top_level.txt