Metadata-Version: 1.0
Name: h5wqueue
Version: 0.1
Summary: Simple utilities for write hdf5 files using workers
Home-page: http://github.com/vmolina/h5wqueue
Author: Victor Bellon Molina
Author-email: vbellon@gmail.com
License: GPLv3
Platform: UNKNOWN
